main.py
setup.py
ic_flows_platform.egg-info/PKG-INFO
ic_flows_platform.egg-info/SOURCES.txt
ic_flows_platform.egg-info/dependency_links.txt
ic_flows_platform.egg-info/requires.txt
ic_flows_platform.egg-info/top_level.txt